[
  {
    "username": "Kaylaavc",
    "Ip": "172.18.0.15",
    "Access": true,
    "Added on": "4/19/2024"
  },
  {
    "username": "yuuru45",
    "Ip": "172.18.0.28",
    "Access": true,
    "Added on": "3/19/2024"
  },
  {
    "username": "ayakaai",
    "Ip": "",
    "Access": true,
    "Added on": "1/14/2024"
  },
  {
    "username": "s22222233",
    "Ip": "",
    "Access": true,
    "Added on": "1/3/2024"
  },
  {
    "username": "pokieexyz",
    "Ip": "172.18.0.13",
    "Access": true,
    "Added on": "4/10/2024"
  }
]
